README.md
setup.py
lib/envario/__init__.py
lib/envario/config.py
lib/envario/env.py
lib/envario.egg-info/PKG-INFO
lib/envario.egg-info/SOURCES.txt
lib/envario.egg-info/dependency_links.txt
lib/envario.egg-info/not-zip-safe
lib/envario.egg-info/top_level.txt